tob/clients.py
tob/command.py
tob/handler.py
tob/loggers.py
tob/marshal.py
tob/methods.py
tob/objects.py
tob/package.py
tob/persist.py
tob/repeats.py
tob/threads.py
tob/utility.py
tob/modules/__init__.py
tob/network/__init__.py
tobot/modules/__init__.py
tobot/modules/flt.py
tobot/modules/fnd.py
tobot/modules/irc.py
tobot/modules/log.py
tobot/modules/lst.py
tobot/modules/man.py
tobot/modules/mbx.py
tobot/modules/mdl.py
tobot/modules/mod.py
tobot/modules/pth.py
tobot/modules/req.py
tobot/modules/rss.py
tobot/modules/rst.py
tobot/modules/sil.py
tobot/modules/slg.py
tobot/modules/tdo.py
tobot/modules/thr.py
tobot/modules/tmr.py
tobot/modules/udp.py
tobot/modules/upt.py
tobot/modules/web.py
tobot/modules/wsd.py
tobot/network/html/index.html
tobot-8.data/scripts/tobot
tobot-8.dist-info/METADATA
tobot-8.dist-info/WHEEL
tobot-8.dist-info/top_level.txt
tobot-8.dist-info/RECORD
