Metadata-Version: 2.4
Name: tobot
Version: 8
Summary: bot in reverse !
Author-email: Bart Thate <bthate@dds.nl>
License-Expression: Unlicense
Project-URL: home, https://pypi.org/project/tobot
Project-URL: bugs, https://github.com/botlibX/tobot/issues
Project-URL: source, https://github.com/botlibX/tobot
Classifier: Development Status :: 3 - Alpha
Classifier: Operating System :: Unix
Classifier: Programming Language :: Python :: 3
Classifier: Topic :: Utilities
